zou/__init__.py
zou/cli.py
zou/debug.py
zou/event_stream.py
zou/job_settings.py
zou/app/__init__.py
zou/app/api.py
zou/app/config.py
zou/app/mixin.py
zou/app/swagger.py
zou/app/blueprints/__init__.py
zou/app/blueprints/assets/__init__.py
zou/app/blueprints/assets/resources.py
zou/app/blueprints/auth/__init__.py
zou/app/blueprints/auth/resources.py
zou/app/blueprints/breakdown/__init__.py
zou/app/blueprints/breakdown/resources.py
zou/app/blueprints/chats/__init__.py
zou/app/blueprints/chats/resources.py
zou/app/blueprints/comments/__init__.py
zou/app/blueprints/comments/resources.py
zou/app/blueprints/concepts/__init__.py
zou/app/blueprints/concepts/resources.py
zou/app/blueprints/crud/__init__.py
zou/app/blueprints/crud/asset_instance.py
zou/app/blueprints/crud/attachment_file.py
zou/app/blueprints/crud/base.py
zou/app/blueprints/crud/budget.py
zou/app/blueprints/crud/budget_entry.py
zou/app/blueprints/crud/chat.py
zou/app/blueprints/crud/chat_message.py
zou/app/blueprints/crud/comments.py
zou/app/blueprints/crud/custom_action.py
zou/app/blueprints/crud/day_off.py
zou/app/blueprints/crud/department.py
zou/app/blueprints/crud/entity.py
zou/app/blueprints/crud/entity_link.py
zou/app/blueprints/crud/entity_type.py
zou/app/blueprints/crud/event.py
zou/app/blueprints/crud/file_status.py
zou/app/blueprints/crud/hardware_item.py
zou/app/blueprints/crud/metadata_descriptor.py
zou/app/blueprints/crud/milestone.py
zou/app/blueprints/crud/news.py
zou/app/blueprints/crud/notification.py
zou/app/blueprints/crud/organisation.py
zou/app/blueprints/crud/output_file.py
zou/app/blueprints/crud/output_type.py
zou/app/blueprints/crud/person.py
zou/app/blueprints/crud/playlist.py
zou/app/blueprints/crud/plugin.py
zou/app/blueprints/crud/preview_background_file.py
zou/app/blueprints/crud/preview_file.py
zou/app/blueprints/crud/production_schedule_version.py
zou/app/blueprints/crud/project.py
zou/app/blueprints/crud/project_status.py
zou/app/blueprints/crud/salary_scale.py
zou-1.0.6.dist-info/licenses/LICENSE
zou-1.0.6.dist-info/METADATA
zou-1.0.6.dist-info/WHEEL
zou-1.0.6.dist-info/entry_points.txt
zou-1.0.6.dist-info/top_level.txt
zou-1.0.6.dist-info/RECORD
