Metadata-Version: 2.4
Name: zou
Version: 1.0.6
Summary: API to store and manage the data of your animation production
Home-page: https://zou.cg-wire.com
Author: CG Wire
Author-email: frank@cg-wire.com
License: GNU Affero General Public License v3
Keywords: animation,cg,asset,shot,api,cg production,asset management
Classifier: Development Status :: 5 - Production/Stable
Classifier: Environment :: Web Environment
Classifier: Framework :: Flask
Classifier: Intended Audience :: Developers
Classifier: Programming Language :: Python :: 3.10
Classifier: Programming Language :: Python :: 3.11
Classifier: Programming Language :: Python :: 3.12
Classifier: Programming Language :: Python :: 3.13
Classifier: Programming Language :: Python :: Implementation :: CPython
Classifier: Programming Language :: Python :: Implementation :: PyPy
Classifier: Topic :: Multimedia :: Graphics
Requires-Python: >=3.10, <3.14
License-File: LICENSE
Requires-Dist: babel==2.17.0
Requires-Dist: click==8.3.1
Requires-Dist: discord.py==2.6.4
Requires-Dist: email-validator==2.3.0
Requires-Dist: ffmpeg-python==0.2.0
Requires-Dist: fido2==2.0.0
Requires-Dist: flasgger==0.9.7.1
Requires-Dist: flask_bcrypt==1.0.1
Requires-Dist: flask_caching==2.3.1
Requires-Dist: flask_fixtures==0.3.8
Requires-Dist: flask_mail==0.10.0
Requires-Dist: flask_principal==0.4.0
Requires-Dist: flask_restful==0.3.10
Requires-Dist: flask_sqlalchemy==3.1.1
Requires-Dist: flask-fs2[s3,swift]==0.7.31
Requires-Dist: flask-jwt-extended==4.7.1
Requires-Dist: flask-migrate==4.1.0
Requires-Dist: flask-socketio==5.5.1
Requires-Dist: flask==3.1.2
Requires-Dist: gazu==1.0.0
Requires-Dist: gevent-websocket==0.10.1
Requires-Dist: gevent==25.9.1
Requires-Dist: gunicorn==23.0.0
Requires-Dist: isoweek==1.3.3
Requires-Dist: itsdangerous==2.2.0
Requires-Dist: Jinja2==3.1.6
Requires-Dist: ldap3==2.9.1
Requires-Dist: matterhook==0.2
Requires-Dist: meilisearch==0.38.0
Requires-Dist: numpy==2.2.6
Requires-Dist: opencv-python==4.12.0.88
Requires-Dist: OpenTimelineIO==0.18.1
Requires-Dist: OpenTimelineIO-Plugins==0.18.1
Requires-Dist: orjson==3.11.4
Requires-Dist: pillow==12.0.0
Requires-Dist: psutil==7.1.3
Requires-Dist: psycopg[binary]==3.2.13
Requires-Dist: pyotp==2.9.0
Requires-Dist: pysaml2==7.5.4
Requires-Dist: python-nomad==2.1.0
Requires-Dist: python-slugify==8.0.4
Requires-Dist: python-socketio==5.15.0
Requires-Dist: pytz==2025.2
Requires-Dist: redis==5.2.1
Requires-Dist: requests==2.32.5
Requires-Dist: rq==2.6.1
Requires-Dist: semver==3.0.4
Requires-Dist: slackclient==2.9.4
Requires-Dist: spdx-license-list==3.27.0
Requires-Dist: sqlalchemy_utils==0.42.0
Requires-Dist: sqlalchemy==2.0.44
Requires-Dist: tabulate==0.9.0
Requires-Dist: tomlkit==0.13.3
Requires-Dist: ua-parser==1.0.1
Requires-Dist: werkzeug==3.1.3
Provides-Extra: prod
Requires-Dist: gunicorn; extra == "prod"
Requires-Dist: gevent; extra == "prod"
Provides-Extra: dev
Requires-Dist: wheel; extra == "dev"
Provides-Extra: test
Requires-Dist: fakeredis==2.32.1; extra == "test"
Requires-Dist: mixer==7.2.2; extra == "test"
Requires-Dist: pytest-cov==7.0.0; extra == "test"
Requires-Dist: pytest==9.0.1; extra == "test"
Provides-Extra: monitoring
Requires-Dist: prometheus-flask-exporter==0.23.2; extra == "monitoring"
Requires-Dist: pygelf==0.4.3; extra == "monitoring"
Requires-Dist: sentry-sdk==2.46.0; extra == "monitoring"
Provides-Extra: lint
Requires-Dist: autoflake==2.3.1; extra == "lint"
Requires-Dist: black==25.11.0; extra == "lint"
Requires-Dist: pre-commit==4.5.0; extra == "lint"
Dynamic: license-file
Dynamic: requires-python
